boring_math/combinatorics/__init__.py
boring_math/combinatorics/py.typed
boring_math_combinatorics-2.0.0.dist-info/licenses/LICENSE
boring_math_combinatorics-2.0.0.dist-info/WHEEL
boring_math_combinatorics-2.0.0.dist-info/METADATA
boring_math_combinatorics-2.0.0.dist-info/RECORD
